fompy/__init__.py
fompy/constants.py
fompy/functions.py
fompy/materials.py
fompy/models.py
fompy/units.py
fompy/util/__init__.py
fompy/util/fermi_dirac.py
fompy/util/parser.py
fompy/util/zeros.py
fti_fompy-0.4.0.dist-info/LICENSE.md
fti_fompy-0.4.0.dist-info/METADATA
fti_fompy-0.4.0.dist-info/WHEEL
fti_fompy-0.4.0.dist-info/top_level.txt
fti_fompy-0.4.0.dist-info/RECORD
