Metadata-Version: 2.1
Name: fti-fompy
Version: 0.4.0
Summary: Routines for the course "Physical Fundamentals of Microelectronics"
Home-page: https://github.com/kononovarseniy/fompy
Author: Arseniy Kononov
Author-email: a.kononov1@g.nsu.ru
License: UNKNOWN
Platform: UNKNOWN
Classifier: Programming Language :: Python :: 3
Classifier: License :: OSI Approved :: MIT License
Classifier: Operating System :: OS Independent
Requires-Python: >=3.6
Requires-Dist: numpy
Requires-Dist: scipy
